midjourney_api_client/__init__.py
midjourney_api_client/api_client.py
midjourney_api_client/api_response.py
midjourney_api_client/configuration.py
midjourney_api_client/exceptions.py
midjourney_api_client/py.typed
midjourney_api_client/rest.py
midjourney_api_client/api/__init__.py
midjourney_api_client/api/default_api.py
midjourney_api_client/models/__init__.py
midjourney_api_client/models/account_response.py
midjourney_api_client/models/blend_response.py
midjourney_api_client/models/button_response.py
midjourney_api_client/models/button_response_error_upscaled.py
midjourney_api_client/models/describe_response.py
midjourney_api_client/models/imagine_response.py
midjourney_api_client/models/imagine_response_moderated.py
midjourney_api_client/models/job_cancel_response.py
midjourney_api_client/models/job_response.py
midjourney_api_client/models/job_response_attachments_inner.py
midjourney_api_client/models/job_response_children_inner.py
midjourney_api_client/models/job_response_embeds_inner.py
midjourney_api_client/models/job_response_embeds_inner_image.py
midjourney_api_client/models/jobs_blend_post_request.py
midjourney_api_client/models/jobs_button_post_request.py
midjourney_api_client/models/jobs_describe_post_request.py
midjourney_api_client/models/jobs_imagine_post_request.py
midjourney_api_client/models/response_error.py
midjourney_api_client/models/response_max_jobs.py
midjourney_api_client-1.0.1.dist-info/METADATA
midjourney_api_client-1.0.1.dist-info/WHEEL
midjourney_api_client-1.0.1.dist-info/top_level.txt
midjourney_api_client-1.0.1.dist-info/RECORD
