Metadata-Version: 2.1
Name: midjourney-api-client
Version: 1.0.1
Summary: Midjourney API by useapi.net
Home-page: https://useapi.net
Author: Use API
Author-email: support@useapi.net
License: ISC
Keywords: Midjourney,API,useapi.net
Classifier: Development Status :: 5 - Production/Stable
Classifier: Intended Audience :: Developers
Classifier: Topic :: Software Development :: Build Tools
Classifier: Programming Language :: Python :: 3
Classifier: Programming Language :: Python :: 3.7
Classifier: Programming Language :: Python :: 3.8
Classifier: Programming Language :: Python :: 3.9
Classifier: Programming Language :: Python :: 3.10
Classifier: Programming Language :: Python :: 3.11
Classifier: Programming Language :: Python :: 3.12
Requires-Dist: urllib3 <2.1.0,>=1.25.3
Requires-Dist: python-dateutil >=2.5.3
Requires-Dist: pydantic <2,>=1.10.5
Requires-Dist: aenum >=3.1.11
